setup.py
irc_helper/__init__.py
irc_helper/irc_protocol.py
irc_helper/main_bot.py
irc_helper.egg-info/PKG-INFO
irc_helper.egg-info/SOURCES.txt
irc_helper.egg-info/dependency_links.txt
irc_helper.egg-info/top_level.txt