Metadata-Version: 1.0
Name: irc-helper
Version: 1.4.3
Summary: A module that helps with IRC, namely IRC Bots.
Home-page: https://github.com/SquishyStrawberry/
Author: SquishyStrawberry
Author-email: squishystrawberry2015@gmail.com
License: UNKNOWN
Platform: UNKNOWN
